README.md
pyproject.toml
setup.py
autoelicit/__init__.py
autoelicit/datasets.py
autoelicit/gpt.py
autoelicit/mc.py
autoelicit/memory_check.py
autoelicit/metrics.py
autoelicit/plotting.py
autoelicit/utils.py
autoelicit.egg-info/PKG-INFO
autoelicit.egg-info/SOURCES.txt
autoelicit.egg-info/dependency_links.txt
autoelicit.egg-info/requires.txt
autoelicit.egg-info/top_level.txt