Metadata-Version: 2.4
Name: autoelicit
Version: 0.1.14
Summary: A python package for eliciting prior knowledge from experts using large language models.
Home-page: https://github.com/alexcapstick/autoelicit
Author: Alexander Capstick
Author-email: alexander.capstick19@imperial.ac.uk
License: MIT
Classifier: Intended Audience :: Science/Research
Classifier: Programming Language :: Python :: 3
Classifier: Programming Language :: Python :: 3.9
Classifier: Programming Language :: Python :: 3.10
Classifier: Programming Language :: Python :: 3.11
Requires-Dist: numpy
Requires-Dist: scipy
Requires-Dist: pandas
Requires-Dist: scikit-learn
Requires-Dist: tqdm
Requires-Dist: pyarrow
Requires-Dist: ucimlrepo
Requires-Dist: openai>=1.51.2
Dynamic: author
Dynamic: author-email
Dynamic: classifier
Dynamic: description
Dynamic: description-content-type
Dynamic: home-page
Dynamic: license
Dynamic: requires-dist
Dynamic: summary
